{
    "lotterys": {
        "奖品229": {
            "total_count": 1,
            "rounds_missed": 0,
            "last_drawn_time": "2026-02-01 15:31:55",
            "history": [
                {
                    "draw_time": "2026-02-01 15:31:55",
                    "draw_lottery_numbers": 5,
                    "draw_group": "抽取全部学生",
                    "draw_gender": "抽取全部性别"
                }
            ]
        },
        "奖品023": {
            "total_count": 1,
            "rounds_missed": 0,
            "last_drawn_time": "2026-02-01 15:31:55",
            "history": [
                {
                    "draw_time": "2026-02-01 15:31:55",
                    "draw_lottery_numbers": 5,
                    "draw_group": "抽取全部学生",
                    "draw_gender": "抽取全部性别"
                }
            ]
        },
        "奖品236": {
            "total_count": 1,
            "rounds_missed": 0,
            "last_drawn_time": "2026-02-01 15:31:55",
            "history": [
                {
                    "draw_time": "2026-02-01 15:31:55",
                    "draw_lottery_numbers": 5,
                    "draw_group": "抽取全部学生",
                    "draw_gender": "抽取全部性别"
                }
            ]
        },
        "奖品361": {
            "total_count": 1,
            "rounds_missed": 0,
            "last_drawn_time": "2026-02-01 15:31:55",
            "history": [
                {
                    "draw_time": "2026-02-01 15:31:55",
                    "draw_lottery_numbers": 5,
                    "draw_group": "抽取全部学生",
                    "draw_gender": "抽取全部性别"
                }
            ]
        },
        "奖品177": {
            "total_count": 1,
            "rounds_missed": 0,
            "last_drawn_time": "2026-02-01 15:31:55",
            "history": [
                {
                    "draw_time": "2026-02-01 15:31:55",
                    "draw_lottery_numbers": 5,
                    "draw_group": "抽取全部学生",
                    "draw_gender": "抽取全部性别"
                }
            ]
        },
        "奖品010": {
            "total_count": 1,
            "rounds_missed": 0,
            "last_drawn_time": "2026-02-01 15:32:36",
            "history": [
                {
                    "draw_time": "2026-02-01 15:32:36",
                    "draw_lottery_numbers": 5,
                    "draw_group": "抽取全部学生",
                    "draw_gender": "抽取全部性别"
                }
            ]
        },
        "奖品251": {
            "total_count": 1,
            "rounds_missed": 0,
            "last_drawn_time": "2026-02-01 15:32:36",
            "history": [
                {
                    "draw_time": "2026-02-01 15:32:36",
                    "draw_lottery_numbers": 5,
                    "draw_group": "抽取全部学生",
                    "draw_gender": "抽取全部性别"
                }
            ]
        },
        "奖品313": {
            "total_count": 1,
            "rounds_missed": 0,
            "last_drawn_time": "2026-02-01 15:32:36",
            "history": [
                {
                    "draw_time": "2026-02-01 15:32:36",
                    "draw_lottery_numbers": 5,
                    "draw_group": "抽取全部学生",
                    "draw_gender": "抽取全部性别"
                }
            ]
        },
        "奖品098": {
            "total_count": 1,
            "rounds_missed": 0,
            "last_drawn_time": "2026-02-01 15:32:36",
            "history": [
                {
                    "draw_time": "2026-02-01 15:32:36",
                    "draw_lottery_numbers": 5,
                    "draw_group": "抽取全部学生",
                    "draw_gender": "抽取全部性别"
                }
            ]
        },
        "奖品260": {
            "total_count": 1,
            "rounds_missed": 0,
            "last_drawn_time": "2026-02-01 15:32:36",
            "history": [
                {
                    "draw_time": "2026-02-01 15:32:36",
                    "draw_lottery_numbers": 5,
                    "draw_group": "抽取全部学生",
                    "draw_gender": "抽取全部性别"
                }
            ]
        },
        "奖品151": {
            "total_count": 1,
            "rounds_missed": 0,
            "last_drawn_time": "2026-02-01 15:32:39",
            "history": [
                {
                    "draw_time": "2026-02-01 15:32:39",
                    "draw_lottery_numbers": 5,
                    "draw_group": "抽取全部小组",
                    "draw_gender": "抽取全部性别"
                }
            ]
        },
        "奖品112": {
            "total_count": 1,
            "rounds_missed": 0,
            "last_drawn_time": "2026-02-01 15:32:39",
            "history": [
                {
                    "draw_time": "2026-02-01 15:32:39",
                    "draw_lottery_numbers": 5,
                    "draw_group": "抽取全部小组",
                    "draw_gender": "抽取全部性别"
                }
            ]
        },
        "奖品363": {
            "total_count": 1,
            "rounds_missed": 0,
            "last_drawn_time": "2026-02-01 15:32:39",
            "history": [
                {
                    "draw_time": "2026-02-01 15:32:39",
                    "draw_lottery_numbers": 5,
                    "draw_group": "抽取全部小组",
                    "draw_gender": "抽取全部性别"
                }
            ]
        },
        "奖品131": {
            "total_count": 1,
            "rounds_missed": 0,
            "last_drawn_time": "2026-02-01 15:32:39",
            "history": [
                {
                    "draw_time": "2026-02-01 15:32:39",
                    "draw_lottery_numbers": 5,
                    "draw_group": "抽取全部小组",
                    "draw_gender": "抽取全部性别"
                }
            ]
        },
        "奖品334": {
            "total_count": 1,
            "rounds_missed": 0,
            "last_drawn_time": "2026-02-01 15:32:39",
            "history": [
                {
                    "draw_time": "2026-02-01 15:32:39",
                    "draw_lottery_numbers": 5,
                    "draw_group": "抽取全部小组",
                    "draw_gender": "抽取全部性别"
                }
            ]
        },
        "奖品053": {
            "total_count": 1,
            "rounds_missed": 0,
            "last_drawn_time": "2026-02-01 15:33:03",
            "history": [
                {
                    "draw_time": "2026-02-01 15:33:03",
                    "draw_lottery_numbers": 5,
                    "draw_group": "抽取全部小组",
                    "draw_gender": "抽取全部性别"
                }
            ]
        },
        "奖品092": {
            "total_count": 1,
            "rounds_missed": 0,
            "last_drawn_time": "2026-02-01 15:33:03",
            "history": [
                {
                    "draw_time": "2026-02-01 15:33:03",
                    "draw_lottery_numbers": 5,
                    "draw_group": "抽取全部小组",
                    "draw_gender": "抽取全部性别"
                }
            ]
        },
        "奖品201": {
            "total_count": 1,
            "rounds_missed": 0,
            "last_drawn_time": "2026-02-01 15:33:03",
            "history": [
                {
                    "draw_time": "2026-02-01 15:33:03",
                    "draw_lottery_numbers": 5,
                    "draw_group": "抽取全部小组",
                    "draw_gender": "抽取全部性别"
                }
            ]
        },
        "奖品121": {
            "total_count": 1,
            "rounds_missed": 0,
            "last_drawn_time": "2026-02-01 15:33:03",
            "history": [
                {
                    "draw_time": "2026-02-01 15:33:03",
                    "draw_lottery_numbers": 5,
                    "draw_group": "抽取全部小组",
                    "draw_gender": "抽取全部性别"
                }
            ]
        },
        "奖品356": {
            "total_count": 1,
            "rounds_missed": 0,
            "last_drawn_time": "2026-02-01 15:33:03",
            "history": [
                {
                    "draw_time": "2026-02-01 15:33:03",
                    "draw_lottery_numbers": 5,
                    "draw_group": "抽取全部小组",
                    "draw_gender": "抽取全部性别"
                }
            ]
        },
        "奖品283": {
            "total_count": 1,
            "rounds_missed": 0,
            "last_drawn_time": "2026-02-01 15:33:04",
            "history": [
                {
                    "draw_time": "2026-02-01 15:33:04",
                    "draw_lottery_numbers": 5,
                    "draw_group": "抽取全部小组",
                    "draw_gender": "抽取全部性别"
                }
            ]
        },
        "奖品067": {
            "total_count": 1,
            "rounds_missed": 0,
            "last_drawn_time": "2026-02-01 15:33:04",
            "history": [
                {
                    "draw_time": "2026-02-01 15:33:04",
                    "draw_lottery_numbers": 5,
                    "draw_group": "抽取全部小组",
                    "draw_gender": "抽取全部性别"
                }
            ]
        },
        "奖品109": {
            "total_count": 1,
            "rounds_missed": 0,
            "last_drawn_time": "2026-02-01 15:33:04",
            "history": [
                {
                    "draw_time": "2026-02-01 15:33:04",
                    "draw_lottery_numbers": 5,
                    "draw_group": "抽取全部小组",
                    "draw_gender": "抽取全部性别"
                }
            ]
        },
        "奖品300": {
            "total_count": 1,
            "rounds_missed": 0,
            "last_drawn_time": "2026-02-01 15:33:04",
            "history": [
                {
                    "draw_time": "2026-02-01 15:33:04",
                    "draw_lottery_numbers": 5,
                    "draw_group": "抽取全部小组",
                    "draw_gender": "抽取全部性别"
                }
            ]
        },
        "奖品073": {
            "total_count": 1,
            "rounds_missed": 0,
            "last_drawn_time": "2026-02-01 15:33:04",
            "history": [
                {
                    "draw_time": "2026-02-01 15:33:04",
                    "draw_lottery_numbers": 5,
                    "draw_group": "抽取全部小组",
                    "draw_gender": "抽取全部性别"
                }
            ]
        },
        "奖品228": {
            "total_count": 1,
            "rounds_missed": 0,
            "last_drawn_time": "2026-02-01 15:33:05",
            "history": [
                {
                    "draw_time": "2026-02-01 15:33:05",
                    "draw_lottery_numbers": 5,
                    "draw_group": "抽取全部小组",
                    "draw_gender": "抽取全部性别"
                }
            ]
        },
        "奖品037": {
            "total_count": 1,
            "rounds_missed": 0,
            "last_drawn_time": "2026-02-01 15:33:05",
            "history": [
                {
                    "draw_time": "2026-02-01 15:33:05",
                    "draw_lottery_numbers": 5,
                    "draw_group": "抽取全部小组",
                    "draw_gender": "抽取全部性别"
                }
            ]
        },
        "奖品069": {
            "total_count": 1,
            "rounds_missed": 0,
            "last_drawn_time": "2026-02-01 15:33:05",
            "history": [
                {
                    "draw_time": "2026-02-01 15:33:05",
                    "draw_lottery_numbers": 5,
                    "draw_group": "抽取全部小组",
                    "draw_gender": "抽取全部性别"
                }
            ]
        },
        "奖品017": {
            "total_count": 1,
            "rounds_missed": 0,
            "last_drawn_time": "2026-02-01 15:33:05",
            "history": [
                {
                    "draw_time": "2026-02-01 15:33:05",
                    "draw_lottery_numbers": 5,
                    "draw_group": "抽取全部小组",
                    "draw_gender": "抽取全部性别"
                }
            ]
        },
        "奖品304": {
            "total_count": 1,
            "rounds_missed": 0,
            "last_drawn_time": "2026-02-01 15:33:05",
            "history": [
                {
                    "draw_time": "2026-02-01 15:33:05",
                    "draw_lottery_numbers": 5,
                    "draw_group": "抽取全部小组",
                    "draw_gender": "抽取全部性别"
                }
            ]
        },
        "奖品107": {
            "total_count": 1,
            "rounds_missed": 0,
            "last_drawn_time": "2026-02-01 15:33:07",
            "history": [
                {
                    "draw_time": "2026-02-01 15:33:07",
                    "draw_lottery_numbers": 5,
                    "draw_group": "抽取全部小组",
                    "draw_gender": "抽取全部性别"
                }
            ]
        },
        "奖品155": {
            "total_count": 1,
            "rounds_missed": 0,
            "last_drawn_time": "2026-02-01 15:33:07",
            "history": [
                {
                    "draw_time": "2026-02-01 15:33:07",
                    "draw_lottery_numbers": 5,
                    "draw_group": "抽取全部小组",
                    "draw_gender": "抽取全部性别"
                }
            ]
        },
        "奖品227": {
            "total_count": 1,
            "rounds_missed": 0,
            "last_drawn_time": "2026-02-01 15:33:07",
            "history": [
                {
                    "draw_time": "2026-02-01 15:33:07",
                    "draw_lottery_numbers": 5,
                    "draw_group": "抽取全部小组",
                    "draw_gender": "抽取全部性别"
                }
            ]
        },
        "奖品013": {
            "total_count": 1,
            "rounds_missed": 0,
            "last_drawn_time": "2026-02-01 15:33:07",
            "history": [
                {
                    "draw_time": "2026-02-01 15:33:07",
                    "draw_lottery_numbers": 5,
                    "draw_group": "抽取全部小组",
                    "draw_gender": "抽取全部性别"
                }
            ]
        },
        "奖品068": {
            "total_count": 1,
            "rounds_missed": 0,
            "last_drawn_time": "2026-02-01 15:33:07",
            "history": [
                {
                    "draw_time": "2026-02-01 15:33:07",
                    "draw_lottery_numbers": 5,
                    "draw_group": "抽取全部小组",
                    "draw_gender": "抽取全部性别"
                }
            ]
        },
        "奖品288": {
            "total_count": 1,
            "rounds_missed": 0,
            "last_drawn_time": "2026-02-01 15:33:30",
            "history": [
                {
                    "draw_time": "2026-02-01 15:33:30",
                    "draw_lottery_numbers": 5,
                    "draw_group": "第一小组",
                    "draw_gender": "抽取全部性别"
                }
            ]
        },
        "奖品208": {
            "total_count": 1,
            "rounds_missed": 0,
            "last_drawn_time": "2026-02-01 15:33:30",
            "history": [
                {
                    "draw_time": "2026-02-01 15:33:30",
                    "draw_lottery_numbers": 5,
                    "draw_group": "第一小组",
                    "draw_gender": "抽取全部性别"
                }
            ]
        },
        "奖品024": {
            "total_count": 1,
            "rounds_missed": 0,
            "last_drawn_time": "2026-02-01 15:33:30",
            "history": [
                {
                    "draw_time": "2026-02-01 15:33:30",
                    "draw_lottery_numbers": 5,
                    "draw_group": "第一小组",
                    "draw_gender": "抽取全部性别"
                }
            ]
        },
        "奖品233": {
            "total_count": 1,
            "rounds_missed": 0,
            "last_drawn_time": "2026-02-01 15:33:30",
            "history": [
                {
                    "draw_time": "2026-02-01 15:33:30",
                    "draw_lottery_numbers": 5,
                    "draw_group": "第一小组",
                    "draw_gender": "抽取全部性别"
                }
            ]
        },
        "奖品052": {
            "total_count": 1,
            "rounds_missed": 0,
            "last_drawn_time": "2026-02-01 15:33:30",
            "history": [
                {
                    "draw_time": "2026-02-01 15:33:30",
                    "draw_lottery_numbers": 5,
                    "draw_group": "第一小组",
                    "draw_gender": "抽取全部性别"
                }
            ]
        },
        "奖品248": {
            "total_count": 1,
            "rounds_missed": 0,
            "last_drawn_time": "2026-02-01 15:33:52",
            "history": [
                {
                    "draw_time": "2026-02-01 15:33:52",
                    "draw_lottery_numbers": 4,
                    "draw_group": "第一小组",
                    "draw_gender": "抽取全部性别"
                }
            ]
        },
        "奖品204": {
            "total_count": 1,
            "rounds_missed": 0,
            "last_drawn_time": "2026-02-01 15:33:52",
            "history": [
                {
                    "draw_time": "2026-02-01 15:33:52",
                    "draw_lottery_numbers": 4,
                    "draw_group": "第一小组",
                    "draw_gender": "抽取全部性别"
                }
            ]
        },
        "奖品075": {
            "total_count": 1,
            "rounds_missed": 0,
            "last_drawn_time": "2026-02-01 15:33:52",
            "history": [
                {
                    "draw_time": "2026-02-01 15:33:52",
                    "draw_lottery_numbers": 4,
                    "draw_group": "第一小组",
                    "draw_gender": "抽取全部性别"
                }
            ]
        },
        "奖品038": {
            "total_count": 1,
            "rounds_missed": 0,
            "last_drawn_time": "2026-02-01 15:33:52",
            "history": [
                {
                    "draw_time": "2026-02-01 15:33:52",
                    "draw_lottery_numbers": 4,
                    "draw_group": "第一小组",
                    "draw_gender": "抽取全部性别"
                }
            ]
        },
        "奖品171": {
            "total_count": 1,
            "rounds_missed": 0,
            "last_drawn_time": "2026-02-01 15:33:54",
            "history": [
                {
                    "draw_time": "2026-02-01 15:33:54",
                    "draw_lottery_numbers": 4,
                    "draw_group": "抽取全部小组",
                    "draw_gender": "抽取全部性别"
                }
            ]
        },
        "奖品009": {
            "total_count": 1,
            "rounds_missed": 0,
            "last_drawn_time": "2026-02-01 15:33:54",
            "history": [
                {
                    "draw_time": "2026-02-01 15:33:54",
                    "draw_lottery_numbers": 4,
                    "draw_group": "抽取全部小组",
                    "draw_gender": "抽取全部性别"
                }
            ]
        },
        "奖品108": {
            "total_count": 1,
            "rounds_missed": 0,
            "last_drawn_time": "2026-02-01 15:33:54",
            "history": [
                {
                    "draw_time": "2026-02-01 15:33:54",
                    "draw_lottery_numbers": 4,
                    "draw_group": "抽取全部小组",
                    "draw_gender": "抽取全部性别"
                }
            ]
        },
        "奖品270": {
            "total_count": 1,
            "rounds_missed": 0,
            "last_drawn_time": "2026-02-01 15:33:54",
            "history": [
                {
                    "draw_time": "2026-02-01 15:33:54",
                    "draw_lottery_numbers": 4,
                    "draw_group": "抽取全部小组",
                    "draw_gender": "抽取全部性别"
                }
            ]
        },
        "奖品134": {
            "total_count": 1,
            "rounds_missed": 0,
            "last_drawn_time": "2026-02-01 15:33:57",
            "history": [
                {
                    "draw_time": "2026-02-01 15:33:57",
                    "draw_lottery_numbers": 3,
                    "draw_group": "抽取全部小组",
                    "draw_gender": "抽取全部性别"
                }
            ]
        },
        "奖品168": {
            "total_count": 1,
            "rounds_missed": 0,
            "last_drawn_time": "2026-02-01 15:33:57",
            "history": [
                {
                    "draw_time": "2026-02-01 15:33:57",
                    "draw_lottery_numbers": 3,
                    "draw_group": "抽取全部小组",
                    "draw_gender": "抽取全部性别"
                }
            ]
        },
        "奖品341": {
            "total_count": 1,
            "rounds_missed": 0,
            "last_drawn_time": "2026-02-01 15:33:57",
            "history": [
                {
                    "draw_time": "2026-02-01 15:33:57",
                    "draw_lottery_numbers": 3,
                    "draw_group": "抽取全部小组",
                    "draw_gender": "抽取全部性别"
                }
            ]
        },
        "奖品116": {
            "total_count": 2,
            "rounds_missed": 0,
            "last_drawn_time": "2026-02-01 15:53:32",
            "history": [
                {
                    "draw_time": "2026-02-01 15:39:48",
                    "draw_lottery_numbers": 5,
                    "draw_group": "抽取全部小组",
                    "draw_gender": "抽取全部性别"
                },
                {
                    "draw_time": "2026-02-01 15:53:32",
                    "draw_lottery_numbers": 6,
                    "draw_group": "抽取全部学生",
                    "draw_gender": "抽取全部性别"
                }
            ]
        },
        "奖品202": {
            "total_count": 1,
            "rounds_missed": 0,
            "last_drawn_time": "2026-02-01 15:39:48",
            "history": [
                {
                    "draw_time": "2026-02-01 15:39:48",
                    "draw_lottery_numbers": 5,
                    "draw_group": "抽取全部小组",
                    "draw_gender": "抽取全部性别"
                }
            ]
        },
        "奖品278": {
            "total_count": 1,
            "rounds_missed": 0,
            "last_drawn_time": "2026-02-01 15:39:48",
            "history": [
                {
                    "draw_time": "2026-02-01 15:39:48",
                    "draw_lottery_numbers": 5,
                    "draw_group": "抽取全部小组",
                    "draw_gender": "抽取全部性别"
                }
            ]
        },
        "奖品263": {
            "total_count": 1,
            "rounds_missed": 0,
            "last_drawn_time": "2026-02-01 15:39:48",
            "history": [
                {
                    "draw_time": "2026-02-01 15:39:48",
                    "draw_lottery_numbers": 5,
                    "draw_group": "抽取全部小组",
                    "draw_gender": "抽取全部性别"
                }
            ]
        },
        "奖品187": {
            "total_count": 1,
            "rounds_missed": 0,
            "last_drawn_time": "2026-02-01 15:39:48",
            "history": [
                {
                    "draw_time": "2026-02-01 15:39:48",
                    "draw_lottery_numbers": 5,
                    "draw_group": "抽取全部小组",
                    "draw_gender": "抽取全部性别"
                }
            ]
        },
        "奖品126": {
            "total_count": 1,
            "rounds_missed": 0,
            "last_drawn_time": "2026-02-01 15:40:02",
            "history": [
                {
                    "draw_time": "2026-02-01 15:40:02",
                    "draw_lottery_numbers": 17,
                    "draw_group": "抽取全部小组",
                    "draw_gender": "抽取全部性别"
                }
            ]
        },
        "奖品351": {
            "total_count": 1,
            "rounds_missed": 0,
            "last_drawn_time": "2026-02-01 15:40:02",
            "history": [
                {
                    "draw_time": "2026-02-01 15:40:02",
                    "draw_lottery_numbers": 17,
                    "draw_group": "抽取全部小组",
                    "draw_gender": "抽取全部性别"
                }
            ]
        },
        "奖品306": {
            "total_count": 1,
            "rounds_missed": 0,
            "last_drawn_time": "2026-02-01 15:40:02",
            "history": [
                {
                    "draw_time": "2026-02-01 15:40:02",
                    "draw_lottery_numbers": 17,
                    "draw_group": "抽取全部小组",
                    "draw_gender": "抽取全部性别"
                }
            ]
        },
        "奖品330": {
            "total_count": 1,
            "rounds_missed": 0,
            "last_drawn_time": "2026-02-01 15:40:02",
            "history": [
                {
                    "draw_time": "2026-02-01 15:40:02",
                    "draw_lottery_numbers": 17,
                    "draw_group": "抽取全部小组",
                    "draw_gender": "抽取全部性别"
                }
            ]
        },
        "奖品080": {
            "total_count": 1,
            "rounds_missed": 0,
            "last_drawn_time": "2026-02-01 15:40:02",
            "history": [
                {
                    "draw_time": "2026-02-01 15:40:02",
                    "draw_lottery_numbers": 17,
                    "draw_group": "抽取全部小组",
                    "draw_gender": "抽取全部性别"
                }
            ]
        },
        "奖品243": {
            "total_count": 1,
            "rounds_missed": 0,
            "last_drawn_time": "2026-02-01 15:40:02",
            "history": [
                {
                    "draw_time": "2026-02-01 15:40:02",
                    "draw_lottery_numbers": 17,
                    "draw_group": "抽取全部小组",
                    "draw_gender": "抽取全部性别"
                }
            ]
        },
        "奖品267": {
            "total_count": 1,
            "rounds_missed": 0,
            "last_drawn_time": "2026-02-01 15:40:02",
            "history": [
                {
                    "draw_time": "2026-02-01 15:40:02",
                    "draw_lottery_numbers": 17,
                    "draw_group": "抽取全部小组",
                    "draw_gender": "抽取全部性别"
                }
            ]
        },
        "奖品220": {
            "total_count": 1,
            "rounds_missed": 0,
            "last_drawn_time": "2026-02-01 15:40:02",
            "history": [
                {
                    "draw_time": "2026-02-01 15:40:02",
                    "draw_lottery_numbers": 17,
                    "draw_group": "抽取全部小组",
                    "draw_gender": "抽取全部性别"
                }
            ]
        },
        "奖品110": {
            "total_count": 1,
            "rounds_missed": 0,
            "last_drawn_time": "2026-02-01 15:40:02",
            "history": [
                {
                    "draw_time": "2026-02-01 15:40:02",
                    "draw_lottery_numbers": 17,
                    "draw_group": "抽取全部小组",
                    "draw_gender": "抽取全部性别"
                }
            ]
        },
        "奖品325": {
            "total_count": 1,
            "rounds_missed": 0,
            "last_drawn_time": "2026-02-01 15:40:02",
            "history": [
                {
                    "draw_time": "2026-02-01 15:40:02",
                    "draw_lottery_numbers": 17,
                    "draw_group": "抽取全部小组",
                    "draw_gender": "抽取全部性别"
                }
            ]
        },
        "奖品194": {
            "total_count": 1,
            "rounds_missed": 0,
            "last_drawn_time": "2026-02-01 15:40:02",
            "history": [
                {
                    "draw_time": "2026-02-01 15:40:02",
                    "draw_lottery_numbers": 17,
                    "draw_group": "抽取全部小组",
                    "draw_gender": "抽取全部性别"
                }
            ]
        },
        "奖品145": {
            "total_count": 1,
            "rounds_missed": 0,
            "last_drawn_time": "2026-02-01 15:40:02",
            "history": [
                {
                    "draw_time": "2026-02-01 15:40:02",
                    "draw_lottery_numbers": 17,
                    "draw_group": "抽取全部小组",
                    "draw_gender": "抽取全部性别"
                }
            ]
        },
        "奖品189": {
            "total_count": 1,
            "rounds_missed": 0,
            "last_drawn_time": "2026-02-01 15:40:02",
            "history": [
                {
                    "draw_time": "2026-02-01 15:40:02",
                    "draw_lottery_numbers": 17,
                    "draw_group": "抽取全部小组",
                    "draw_gender": "抽取全部性别"
                }
            ]
        },
        "奖品192": {
            "total_count": 1,
            "rounds_missed": 0,
            "last_drawn_time": "2026-02-01 15:40:02",
            "history": [
                {
                    "draw_time": "2026-02-01 15:40:02",
                    "draw_lottery_numbers": 17,
                    "draw_group": "抽取全部小组",
                    "draw_gender": "抽取全部性别"
                }
            ]
        },
        "奖品014": {
            "total_count": 1,
            "rounds_missed": 0,
            "last_drawn_time": "2026-02-01 15:40:02",
            "history": [
                {
                    "draw_time": "2026-02-01 15:40:02",
                    "draw_lottery_numbers": 17,
                    "draw_group": "抽取全部小组",
                    "draw_gender": "抽取全部性别"
                }
            ]
        },
        "奖品132": {
            "total_count": 1,
            "rounds_missed": 0,
            "last_drawn_time": "2026-02-01 15:40:02",
            "history": [
                {
                    "draw_time": "2026-02-01 15:40:02",
                    "draw_lottery_numbers": 17,
                    "draw_group": "抽取全部小组",
                    "draw_gender": "抽取全部性别"
                }
            ]
        },
        "奖品255": {
            "total_count": 1,
            "rounds_missed": 0,
            "last_drawn_time": "2026-02-01 15:40:02",
            "history": [
                {
                    "draw_time": "2026-02-01 15:40:02",
                    "draw_lottery_numbers": 17,
                    "draw_group": "抽取全部小组",
                    "draw_gender": "抽取全部性别"
                }
            ]
        },
        "奖品244": {
            "total_count": 1,
            "rounds_missed": 0,
            "last_drawn_time": "2026-02-01 15:40:15",
            "history": [
                {
                    "draw_time": "2026-02-01 15:40:15",
                    "draw_lottery_numbers": 17,
                    "draw_group": "抽取全部小组",
                    "draw_gender": "抽取全部性别"
                }
            ]
        },
        "奖品041": {
            "total_count": 1,
            "rounds_missed": 0,
            "last_drawn_time": "2026-02-01 15:40:15",
            "history": [
                {
                    "draw_time": "2026-02-01 15:40:15",
                    "draw_lottery_numbers": 17,
                    "draw_group": "抽取全部小组",
                    "draw_gender": "抽取全部性别"
                }
            ]
        },
        "奖品210": {
            "total_count": 1,
            "rounds_missed": 0,
            "last_drawn_time": "2026-02-01 15:40:15",
            "history": [
                {
                    "draw_time": "2026-02-01 15:40:15",
                    "draw_lottery_numbers": 17,
                    "draw_group": "抽取全部小组",
                    "draw_gender": "抽取全部性别"
                }
            ]
        },
        "奖品291": {
            "total_count": 1,
            "rounds_missed": 0,
            "last_drawn_time": "2026-02-01 15:40:15",
            "history": [
                {
                    "draw_time": "2026-02-01 15:40:15",
                    "draw_lottery_numbers": 17,
                    "draw_group": "抽取全部小组",
                    "draw_gender": "抽取全部性别"
                }
            ]
        },
        "奖品303": {
            "total_count": 1,
            "rounds_missed": 0,
            "last_drawn_time": "2026-02-01 15:40:15",
            "history": [
                {
                    "draw_time": "2026-02-01 15:40:15",
                    "draw_lottery_numbers": 17,
                    "draw_group": "抽取全部小组",
                    "draw_gender": "抽取全部性别"
                }
            ]
        },
        "奖品099": {
            "total_count": 1,
            "rounds_missed": 0,
            "last_drawn_time": "2026-02-01 15:40:15",
            "history": [
                {
                    "draw_time": "2026-02-01 15:40:15",
                    "draw_lottery_numbers": 17,
                    "draw_group": "抽取全部小组",
                    "draw_gender": "抽取全部性别"
                }
            ]
        },
        "奖品282": {
            "total_count": 1,
            "rounds_missed": 0,
            "last_drawn_time": "2026-02-01 15:40:15",
            "history": [
                {
                    "draw_time": "2026-02-01 15:40:15",
                    "draw_lottery_numbers": 17,
                    "draw_group": "抽取全部小组",
                    "draw_gender": "抽取全部性别"
                }
            ]
        },
        "奖品035": {
            "total_count": 1,
            "rounds_missed": 0,
            "last_drawn_time": "2026-02-01 15:40:15",
            "history": [
                {
                    "draw_time": "2026-02-01 15:40:15",
                    "draw_lottery_numbers": 17,
                    "draw_group": "抽取全部小组",
                    "draw_gender": "抽取全部性别"
                }
            ]
        },
        "奖品301": {
            "total_count": 1,
            "rounds_missed": 0,
            "last_drawn_time": "2026-02-01 15:40:15",
            "history": [
                {
                    "draw_time": "2026-02-01 15:40:15",
                    "draw_lottery_numbers": 17,
                    "draw_group": "抽取全部小组",
                    "draw_gender": "抽取全部性别"
                }
            ]
        },
        "奖品276": {
            "total_count": 1,
            "rounds_missed": 0,
            "last_drawn_time": "2026-02-01 15:40:15",
            "history": [
                {
                    "draw_time": "2026-02-01 15:40:15",
                    "draw_lottery_numbers": 17,
                    "draw_group": "抽取全部小组",
                    "draw_gender": "抽取全部性别"
                }
            ]
        },
        "奖品074": {
            "total_count": 1,
            "rounds_missed": 0,
            "last_drawn_time": "2026-02-01 15:40:15",
            "history": [
                {
                    "draw_time": "2026-02-01 15:40:15",
                    "draw_lottery_numbers": 17,
                    "draw_group": "抽取全部小组",
                    "draw_gender": "抽取全部性别"
                }
            ]
        },
        "奖品055": {
            "total_count": 1,
            "rounds_missed": 0,
            "last_drawn_time": "2026-02-01 15:40:15",
            "history": [
                {
                    "draw_time": "2026-02-01 15:40:15",
                    "draw_lottery_numbers": 17,
                    "draw_group": "抽取全部小组",
                    "draw_gender": "抽取全部性别"
                }
            ]
        },
        "奖品205": {
            "total_count": 1,
            "rounds_missed": 0,
            "last_drawn_time": "2026-02-01 15:40:15",
            "history": [
                {
                    "draw_time": "2026-02-01 15:40:15",
                    "draw_lottery_numbers": 17,
                    "draw_group": "抽取全部小组",
                    "draw_gender": "抽取全部性别"
                }
            ]
        },
        "奖品163": {
            "total_count": 1,
            "rounds_missed": 0,
            "last_drawn_time": "2026-02-01 15:40:15",
            "history": [
                {
                    "draw_time": "2026-02-01 15:40:15",
                    "draw_lottery_numbers": 17,
                    "draw_group": "抽取全部小组",
                    "draw_gender": "抽取全部性别"
                }
            ]
        },
        "奖品239": {
            "total_count": 1,
            "rounds_missed": 0,
            "last_drawn_time": "2026-02-01 15:40:15",
            "history": [
                {
                    "draw_time": "2026-02-01 15:40:15",
                    "draw_lottery_numbers": 17,
                    "draw_group": "抽取全部小组",
                    "draw_gender": "抽取全部性别"
                }
            ]
        },
        "奖品130": {
            "total_count": 1,
            "rounds_missed": 0,
            "last_drawn_time": "2026-02-01 15:40:15",
            "history": [
                {
                    "draw_time": "2026-02-01 15:40:15",
                    "draw_lottery_numbers": 17,
                    "draw_group": "抽取全部小组",
                    "draw_gender": "抽取全部性别"
                }
            ]
        },
        "奖品096": {
            "total_count": 1,
            "rounds_missed": 0,
            "last_drawn_time": "2026-02-01 15:40:15",
            "history": [
                {
                    "draw_time": "2026-02-01 15:40:15",
                    "draw_lottery_numbers": 17,
                    "draw_group": "抽取全部小组",
                    "draw_gender": "抽取全部性别"
                }
            ]
        },
        "奖品360": {
            "total_count": 1,
            "rounds_missed": 0,
            "last_drawn_time": "2026-02-01 15:47:39",
            "history": [
                {
                    "draw_time": "2026-02-01 15:47:39",
                    "draw_lottery_numbers": 8,
                    "draw_group": "抽取全部学生",
                    "draw_gender": "抽取全部性别"
                }
            ]
        },
        "奖品008": {
            "total_count": 1,
            "rounds_missed": 0,
            "last_drawn_time": "2026-02-01 15:47:39",
            "history": [
                {
                    "draw_time": "2026-02-01 15:47:39",
                    "draw_lottery_numbers": 8,
                    "draw_group": "抽取全部学生",
                    "draw_gender": "抽取全部性别"
                }
            ]
        },
        "奖品221": {
            "total_count": 1,
            "rounds_missed": 0,
            "last_drawn_time": "2026-02-01 15:47:39",
            "history": [
                {
                    "draw_time": "2026-02-01 15:47:39",
                    "draw_lottery_numbers": 8,
                    "draw_group": "抽取全部学生",
                    "draw_gender": "抽取全部性别"
                }
            ]
        },
        "奖品312": {
            "total_count": 1,
            "rounds_missed": 0,
            "last_drawn_time": "2026-02-01 15:47:39",
            "history": [
                {
                    "draw_time": "2026-02-01 15:47:39",
                    "draw_lottery_numbers": 8,
                    "draw_group": "抽取全部学生",
                    "draw_gender": "抽取全部性别"
                }
            ]
        },
        "奖品352": {
            "total_count": 1,
            "rounds_missed": 0,
            "last_drawn_time": "2026-02-01 15:47:39",
            "history": [
                {
                    "draw_time": "2026-02-01 15:47:39",
                    "draw_lottery_numbers": 8,
                    "draw_group": "抽取全部学生",
                    "draw_gender": "抽取全部性别"
                }
            ]
        },
        "奖品136": {
            "total_count": 1,
            "rounds_missed": 0,
            "last_drawn_time": "2026-02-01 15:47:39",
            "history": [
                {
                    "draw_time": "2026-02-01 15:47:39",
                    "draw_lottery_numbers": 8,
                    "draw_group": "抽取全部学生",
                    "draw_gender": "抽取全部性别"
                }
            ]
        },
        "奖品072": {
            "total_count": 1,
            "rounds_missed": 0,
            "last_drawn_time": "2026-02-01 15:47:39",
            "history": [
                {
                    "draw_time": "2026-02-01 15:47:39",
                    "draw_lottery_numbers": 8,
                    "draw_group": "抽取全部学生",
                    "draw_gender": "抽取全部性别"
                }
            ]
        },
        "奖品006": {
            "total_count": 1,
            "rounds_missed": 0,
            "last_drawn_time": "2026-02-01 15:47:39",
            "history": [
                {
                    "draw_time": "2026-02-01 15:47:39",
                    "draw_lottery_numbers": 8,
                    "draw_group": "抽取全部学生",
                    "draw_gender": "抽取全部性别"
                }
            ]
        },
        "奖品284": {
            "total_count": 1,
            "rounds_missed": 0,
            "last_drawn_time": "2026-02-01 15:50:47",
            "history": [
                {
                    "draw_time": "2026-02-01 15:50:47",
                    "draw_lottery_numbers": 8,
                    "draw_group": "抽取全部学生",
                    "draw_gender": "抽取全部性别"
                }
            ]
        },
        "奖品272": {
            "total_count": 1,
            "rounds_missed": 0,
            "last_drawn_time": "2026-02-01 15:50:47",
            "history": [
                {
                    "draw_time": "2026-02-01 15:50:47",
                    "draw_lottery_numbers": 8,
                    "draw_group": "抽取全部学生",
                    "draw_gender": "抽取全部性别"
                }
            ]
        },
        "奖品328": {
            "total_count": 1,
            "rounds_missed": 0,
            "last_drawn_time": "2026-02-01 15:50:47",
            "history": [
                {
                    "draw_time": "2026-02-01 15:50:47",
                    "draw_lottery_numbers": 8,
                    "draw_group": "抽取全部学生",
                    "draw_gender": "抽取全部性别"
                }
            ]
        },
        "奖品046": {
            "total_count": 1,
            "rounds_missed": 0,
            "last_drawn_time": "2026-02-01 15:50:47",
            "history": [
                {
                    "draw_time": "2026-02-01 15:50:47",
                    "draw_lottery_numbers": 8,
                    "draw_group": "抽取全部学生",
                    "draw_gender": "抽取全部性别"
                }
            ]
        },
        "奖品111": {
            "total_count": 1,
            "rounds_missed": 0,
            "last_drawn_time": "2026-02-01 15:50:47",
            "history": [
                {
                    "draw_time": "2026-02-01 15:50:47",
                    "draw_lottery_numbers": 8,
                    "draw_group": "抽取全部学生",
                    "draw_gender": "抽取全部性别"
                }
            ]
        },
        "奖品297": {
            "total_count": 1,
            "rounds_missed": 0,
            "last_drawn_time": "2026-02-01 15:50:47",
            "history": [
                {
                    "draw_time": "2026-02-01 15:50:47",
                    "draw_lottery_numbers": 8,
                    "draw_group": "抽取全部学生",
                    "draw_gender": "抽取全部性别"
                }
            ]
        },
        "奖品133": {
            "total_count": 1,
            "rounds_missed": 0,
            "last_drawn_time": "2026-02-01 15:50:47",
            "history": [
                {
                    "draw_time": "2026-02-01 15:50:47",
                    "draw_lottery_numbers": 8,
                    "draw_group": "抽取全部学生",
                    "draw_gender": "抽取全部性别"
                }
            ]
        },
        "奖品143": {
            "total_count": 1,
            "rounds_missed": 0,
            "last_drawn_time": "2026-02-01 15:50:47",
            "history": [
                {
                    "draw_time": "2026-02-01 15:50:47",
                    "draw_lottery_numbers": 8,
                    "draw_group": "抽取全部学生",
                    "draw_gender": "抽取全部性别"
                }
            ]
        },
        "奖品032": {
            "total_count": 1,
            "rounds_missed": 0,
            "last_drawn_time": "2026-02-01 15:50:49",
            "history": [
                {
                    "draw_time": "2026-02-01 15:50:49",
                    "draw_lottery_numbers": 10,
                    "draw_group": "抽取全部学生",
                    "draw_gender": "抽取全部性别"
                }
            ]
        },
        "奖品302": {
            "total_count": 1,
            "rounds_missed": 0,
            "last_drawn_time": "2026-02-01 15:50:49",
            "history": [
                {
                    "draw_time": "2026-02-01 15:50:49",
                    "draw_lottery_numbers": 10,
                    "draw_group": "抽取全部学生",
                    "draw_gender": "抽取全部性别"
                }
            ]
        },
        "奖品076": {
            "total_count": 1,
            "rounds_missed": 0,
            "last_drawn_time": "2026-02-01 15:50:49",
            "history": [
                {
                    "draw_time": "2026-02-01 15:50:49",
                    "draw_lottery_numbers": 10,
                    "draw_group": "抽取全部学生",
                    "draw_gender": "抽取全部性别"
                }
            ]
        },
        "奖品004": {
            "total_count": 1,
            "rounds_missed": 0,
            "last_drawn_time": "2026-02-01 15:50:49",
            "history": [
                {
                    "draw_time": "2026-02-01 15:50:49",
                    "draw_lottery_numbers": 10,
                    "draw_group": "抽取全部学生",
                    "draw_gender": "抽取全部性别"
                }
            ]
        },
        "奖品117": {
            "total_count": 1,
            "rounds_missed": 0,
            "last_drawn_time": "2026-02-01 15:50:49",
            "history": [
                {
                    "draw_time": "2026-02-01 15:50:49",
                    "draw_lottery_numbers": 10,
                    "draw_group": "抽取全部学生",
                    "draw_gender": "抽取全部性别"
                }
            ]
        },
        "奖品292": {
            "total_count": 1,
            "rounds_missed": 0,
            "last_drawn_time": "2026-02-01 15:50:49",
            "history": [
                {
                    "draw_time": "2026-02-01 15:50:49",
                    "draw_lottery_numbers": 10,
                    "draw_group": "抽取全部学生",
                    "draw_gender": "抽取全部性别"
                }
            ]
        },
        "奖品022": {
            "total_count": 1,
            "rounds_missed": 0,
            "last_drawn_time": "2026-02-01 15:50:49",
            "history": [
                {
                    "draw_time": "2026-02-01 15:50:49",
                    "draw_lottery_numbers": 10,
                    "draw_group": "抽取全部学生",
                    "draw_gender": "抽取全部性别"
                }
            ]
        },
        "奖品176": {
            "total_count": 1,
            "rounds_missed": 0,
            "last_drawn_time": "2026-02-01 15:50:49",
            "history": [
                {
                    "draw_time": "2026-02-01 15:50:49",
                    "draw_lottery_numbers": 10,
                    "draw_group": "抽取全部学生",
                    "draw_gender": "抽取全部性别"
                }
            ]
        },
        "奖品160": {
            "total_count": 1,
            "rounds_missed": 0,
            "last_drawn_time": "2026-02-01 15:50:49",
            "history": [
                {
                    "draw_time": "2026-02-01 15:50:49",
                    "draw_lottery_numbers": 10,
                    "draw_group": "抽取全部学生",
                    "draw_gender": "抽取全部性别"
                }
            ]
        },
        "奖品308": {
            "total_count": 1,
            "rounds_missed": 0,
            "last_drawn_time": "2026-02-01 15:50:49",
            "history": [
                {
                    "draw_time": "2026-02-01 15:50:49",
                    "draw_lottery_numbers": 10,
                    "draw_group": "抽取全部学生",
                    "draw_gender": "抽取全部性别"
                }
            ]
        },
        "奖品345": {
            "total_count": 1,
            "rounds_missed": 0,
            "last_drawn_time": "2026-02-01 15:52:52",
            "history": [
                {
                    "draw_time": "2026-02-01 15:52:52",
                    "draw_lottery_numbers": 7,
                    "draw_group": "抽取全部学生",
                    "draw_gender": "抽取全部性别"
                }
            ]
        },
        "奖品338": {
            "total_count": 1,
            "rounds_missed": 0,
            "last_drawn_time": "2026-02-01 15:52:52",
            "history": [
                {
                    "draw_time": "2026-02-01 15:52:52",
                    "draw_lottery_numbers": 7,
                    "draw_group": "抽取全部学生",
                    "draw_gender": "抽取全部性别"
                }
            ]
        },
        "奖品127": {
            "total_count": 1,
            "rounds_missed": 0,
            "last_drawn_time": "2026-02-01 15:52:52",
            "history": [
                {
                    "draw_time": "2026-02-01 15:52:52",
                    "draw_lottery_numbers": 7,
                    "draw_group": "抽取全部学生",
                    "draw_gender": "抽取全部性别"
                }
            ]
        },
        "奖品101": {
            "total_count": 1,
            "rounds_missed": 0,
            "last_drawn_time": "2026-02-01 15:52:52",
            "history": [
                {
                    "draw_time": "2026-02-01 15:52:52",
                    "draw_lottery_numbers": 7,
                    "draw_group": "抽取全部学生",
                    "draw_gender": "抽取全部性别"
                }
            ]
        },
        "奖品002": {
            "total_count": 1,
            "rounds_missed": 0,
            "last_drawn_time": "2026-02-01 15:52:52",
            "history": [
                {
                    "draw_time": "2026-02-01 15:52:52",
                    "draw_lottery_numbers": 7,
                    "draw_group": "抽取全部学生",
                    "draw_gender": "抽取全部性别"
                }
            ]
        },
        "奖品077": {
            "total_count": 1,
            "rounds_missed": 0,
            "last_drawn_time": "2026-02-01 15:52:52",
            "history": [
                {
                    "draw_time": "2026-02-01 15:52:52",
                    "draw_lottery_numbers": 7,
                    "draw_group": "抽取全部学生",
                    "draw_gender": "抽取全部性别"
                }
            ]
        },
        "奖品223": {
            "total_count": 1,
            "rounds_missed": 0,
            "last_drawn_time": "2026-02-01 15:52:52",
            "history": [
                {
                    "draw_time": "2026-02-01 15:52:52",
                    "draw_lottery_numbers": 7,
                    "draw_group": "抽取全部学生",
                    "draw_gender": "抽取全部性别"
                }
            ]
        },
        "奖品025": {
            "total_count": 1,
            "rounds_missed": 0,
            "last_drawn_time": "2026-02-01 15:53:32",
            "history": [
                {
                    "draw_time": "2026-02-01 15:53:32",
                    "draw_lottery_numbers": 6,
                    "draw_group": "抽取全部学生",
                    "draw_gender": "抽取全部性别"
                }
            ]
        },
        "奖品226": {
            "total_count": 1,
            "rounds_missed": 0,
            "last_drawn_time": "2026-02-01 15:53:32",
            "history": [
                {
                    "draw_time": "2026-02-01 15:53:32",
                    "draw_lottery_numbers": 6,
                    "draw_group": "抽取全部学生",
                    "draw_gender": "抽取全部性别"
                }
            ]
        },
        "奖品007": {
            "total_count": 1,
            "rounds_missed": 0,
            "last_drawn_time": "2026-02-01 15:53:32",
            "history": [
                {
                    "draw_time": "2026-02-01 15:53:32",
                    "draw_lottery_numbers": 6,
                    "draw_group": "抽取全部学生",
                    "draw_gender": "抽取全部性别"
                }
            ]
        },
        "奖品175": {
            "total_count": 1,
            "rounds_missed": 0,
            "last_drawn_time": "2026-02-01 15:53:32",
            "history": [
                {
                    "draw_time": "2026-02-01 15:53:32",
                    "draw_lottery_numbers": 6,
                    "draw_group": "抽取全部学生",
                    "draw_gender": "抽取全部性别"
                }
            ]
        },
        "奖品266": {
            "total_count": 1,
            "rounds_missed": 0,
            "last_drawn_time": "2026-02-01 15:53:32",
            "history": [
                {
                    "draw_time": "2026-02-01 15:53:32",
                    "draw_lottery_numbers": 6,
                    "draw_group": "抽取全部学生",
                    "draw_gender": "抽取全部性别"
                }
            ]
        }
    },
    "group_stats": {
        "抽取全部学生": 49,
        "抽取全部小组": 71,
        "第一小组": 9
    },
    "gender_stats": {
        "抽取全部性别": 129
    },
    "total_stats": 129
}